MANIFEST.in
README.rst
buildout.cfg
develop.cfg
requirements.txt
setup.py
version.txt
bob/__init__.py
bob.db.ijba.egg-info/PKG-INFO
bob.db.ijba.egg-info/SOURCES.txt
bob.db.ijba.egg-info/dependency_links.txt
bob.db.ijba.egg-info/entry_points.txt
bob.db.ijba.egg-info/not-zip-safe
bob.db.ijba.egg-info/requires.txt
bob.db.ijba.egg-info/top_level.txt
bob/db/__init__.py
bob/db/ijba/__init__.py
bob/db/ijba/driver.py
bob/db/ijba/files.txt
bob/db/ijba/query.py
bob/db/ijba/reader.py
bob/db/ijba/test.py
bob/db/ijba/scripts/__init__.py
bob/db/ijba/scripts/score_generation.py
doc/conf.py
doc/guide.rst
doc/index.rst
doc/py_api.rst
doc/img/CMC_ijba.png
doc/img/ROC_ijba.png
doc/img/favicon.ico
doc/img/logo.png